bubblejail/__init__.py
bubblejail/bubblejail_cli.py
bubblejail/bubblejail_helper.py
bubblejail/bubblejail_instance.py
bubblejail/bubblejail_utils.py
bubblejail/bwrap_config.py
bubblejail/exceptions.py
bubblejail/services.py
bubblejail/profiles/code_oss.toml
bubblejail/profiles/firefox.toml
bubblejail/profiles/firefox_wayland.toml
bubblejail/profiles/lutris.toml
bubblejail/profiles/steam.toml
bubblejail-0.2.dist-info/COPYING
bubblejail-0.2.dist-info/METADATA
bubblejail-0.2.dist-info/WHEEL
bubblejail-0.2.dist-info/entry_points.txt
bubblejail-0.2.dist-info/top_level.txt
bubblejail-0.2.dist-info/RECORD
