Metadata-Version: 2.1
Name: bubblejail
Version: 0.2
Summary: Use AUR to install bubblejail. PyPI package is only to hold place.
Home-page: https://github.com/igo95862/bubblejail
Author: UNKNOWN
Author-email: UNKNOWN
License: UNKNOWN
Platform: UNKNOWN
